mlctl/__init__.py
mlctl/__version.py
mlctl/utils.py
mlctl/clis/__init__.py
mlctl/clis/batch_cli.py
mlctl/clis/cli.py
mlctl/clis/hosting_cli.py
mlctl/clis/init_cli.py
mlctl/clis/train_cli.py
mlctl/clis/template/cookiecutter.json
mlctl/clis/template/{{cookiecutter.project_slug}}/.gitignore
mlctl/clis/template/{{cookiecutter.project_slug}}/README.md
mlctl/clis/template/{{cookiecutter.project_slug}}/setup.cfg
mlctl/clis/template/{{cookiecutter.project_slug}}/setup.py
mlctl/clis/template/{{cookiecutter.project_slug}}/tox.ini
mlctl/clis/template/{{cookiecutter.project_slug}}/.github/ISSUE_TEMPLATE.md
mlctl/clis/template/{{cookiecutter.project_slug}}/model/__init__.py
mlctl/clis/template/{{cookiecutter.project_slug}}/model/predict.py
mlctl/clis/template/{{cookiecutter.project_slug}}/model/train.py
mlctl/clis/template/{{cookiecutter.project_slug}}/tests/__init__.py
mlctl/clis/template/{{cookiecutter.project_slug}}/tests/test_{{cookiecutter.project_slug}}.py
mlctl/helpers/__init__.py
mlctl/helpers/log_helper.py
mlctl/interfaces/Batch.py
mlctl/interfaces/Hosting.py
mlctl/interfaces/Training.py
mlctl/interfaces/__init__.py
mlctl/plugins/__init__.py
mlctl/plugins/utils.py
mlctl/plugins/sagemaker/SagemakerBatch.py
mlctl/plugins/sagemaker/SagemakerHosting.py
mlctl/plugins/sagemaker/SagemakerTraining.py
mlctl/plugins/sagemaker/__init__.py
mlctl/usage/SagemakerUsage.md
mlctl-0.0.5.dist-info/LICENSE
mlctl-0.0.5.dist-info/METADATA
mlctl-0.0.5.dist-info/WHEEL
mlctl-0.0.5.dist-info/entry_points.txt
mlctl-0.0.5.dist-info/top_level.txt
mlctl-0.0.5.dist-info/RECORD
